{
    "Empada ou empad\u00e3o nota 1000": {
        "url": "http://www.tudogostoso.com.br/receita/63333-empada-ou-empadao-nota-1000.html",
        "title": "Empada ou empad\u00e3o nota 1000",
        "likes": "  626 ",
        "rating": " 5 ",
        "author": "Gleicy Viana",
        "image_url": "http://img.itdg.com.br/tdg/images/recipes/000/063/333/230276/230276_original.jpg?mode=crop&width=200&height=165"
    },
    "Empad\u00e3o de palmito com iogurte": {
        "url": "http://www.tudogostoso.com.br/receita/66345-empadao-de-palmito-com-iogurte.html",
        "title": "Empad\u00e3o de palmito com iogurte",
        "likes": "  446 ",
        "rating": " 5 ",
        "author": "Gislaine",
        "image_url": "http://img.itdg.com.br/tdg/images/recipes/000/066/345/61999/61999_original.jpg?mode=crop&width=200&height=165"
    },
    "Empad\u00e3o de frango da Judy": {
        "url": "http://www.tudogostoso.com.br/receita/160609-empadao-de-frango-da-judy.html",
        "title": "Empad\u00e3o de frango da Judy",
        "likes": "  28 ",
        "rating": " 5 ",
        "author": "judy",
        "image_url": "http://img.itdg.com.br/tdg/images/recipes/000/160/609/118016/118016_original.jpg?mode=crop&width=200&height=165"
    },
    "Empad\u00e3o de bacalhau ao molho branco": {
        "url": "http://www.tudogostoso.com.br/receita/166741-empadao-de-bacalhau-ao-molho-branco.html",
        "title": "Empad\u00e3o de bacalhau ao molho branco",
        "likes": "  426 ",
        "rating": " 5 ",
        "author": "Tatiane",
        "image_url": "http://img.itdg.com.br/tdg/images/recipes/000/166/741/137399/137399_original.jpg?mode=crop&width=200&height=165"
    },
    "Empad\u00e3o de liquidificador": {
        "url": "http://www.tudogostoso.com.br/receita/26909-empadao-de-liquidificador.html",
        "title": "Empad\u00e3o de liquidificador",
        "likes": "  5.734 ",
        "rating": " 4.5 ",
        "author": "Mariana Oliveira de Oliveira",
        "image_url": "http://img.itdg.com.br/tdg/images/recipes/000/026/909/48041/48041_original.jpg?mode=crop&width=200&height=165"
    },
    "Empad\u00e3o de Frango da Glaucia": {
        "url": "http://www.tudogostoso.com.br/receita/5324-empadao-de-frango-da-glaucia.html",
        "title": "Empad\u00e3o de Frango da Glaucia",
        "likes": "  2.530 ",
        "rating": " 4.5 ",
        "author": "Glaucia Martini",
        "image_url": "http://img.itdg.com.br/tdg/images/recipes/000/005/324/109255/109255_original.jpg?mode=crop&width=200&height=165"
    },
    "Empad\u00e3o de frango com palmito": {
        "url": "http://www.tudogostoso.com.br/receita/157800-empadao-de-frango-com-palmito.html",
        "title": "Empad\u00e3o de frango com palmito",
        "likes": "  1.607 ",
        "rating": " 4.5 ",
        "author": "Priscila",
        "image_url": "http://img.itdg.com.br/tdg/images/recipes/000/157/800/108692/108692_original.jpg?mode=crop&width=200&height=165"
    },
    "Empad\u00e3o de atum e queijo": {
        "url": "http://www.tudogostoso.com.br/receita/67701-empadao-de-atum-e-queijo.html",
        "title": "Empad\u00e3o de atum e queijo",
        "likes": "  416 ",
        "rating": " 5 ",
        "author": "patricia",
        "image_url": "http://img.itdg.com.br/tdg/images/recipes/000/067/701/171250/171250_original.jpg?mode=crop&width=200&height=165"
    },
    "Empad\u00e3o de frango super f\u00e1cil": {
        "url": "http://www.tudogostoso.com.br/receita/21076-empadao-de-frango-super-facil.html",
        "title": "Empad\u00e3o de frango super f\u00e1cil",
        "likes": "  3.643 ",
        "rating": " 4.5 ",
        "author": "Natalia",
        "image_url": "http://img.itdg.com.br/tdg/images/recipes/000/021/076/22525/22525_original.jpg?mode=crop&width=200&height=165"
    },
    "Empad\u00e3o de sardinha": {
        "url": "http://www.tudogostoso.com.br/receita/66020-empadao-de-sardinha.html",
        "title": "Empad\u00e3o de sardinha",
        "likes": "  393 ",
        "rating": " 4.5 ",
        "author": "Michelle",
        "image_url": "http://img.itdg.com.br/tdg/images/recipes/000/066/020/12449/12449_original.jpg?mode=crop&width=200&height=165"
    }
}